Hyper/Configurator.py
Hyper/DataBase.py
Hyper/Errors.py
Hyper/Events.py
Hyper/Listener.py
Hyper/Logger.py
Hyper/Manager.py
Hyper/Network.py
Hyper/Segments.py
Hyper/Adapters/OneBot.py
Hyper/Adapters/Satori.py
Hyper/Adapters/OneBotLib/Manager.py
Hyper/Adapters/OneBotLib/Res.py
Hyper/Utils/Logic.py
Hyper/Utils/TypeExt.py
hyper_bot-0.772.dist-info/LICENSE
hyper_bot-0.772.dist-info/METADATA
hyper_bot-0.772.dist-info/WHEEL
hyper_bot-0.772.dist-info/top_level.txt
hyper_bot-0.772.dist-info/RECORD
