Metadata-Version: 2.1
Name: hyper-bot
Version: 0.772
Summary: 稳定高效、易于开发的QQ Bot框架
Home-page: https://github.com/HarcicYang/HypeR_Bot
Author: Harcic
Author-email: harcic@outlook.com
License-File: LICENSE
